MANIFEST.in
README.rst
setup.py
version
src/turf/__init__.py
src/turf/config.py
src/turf/errors.py
src/turf/s3config.py
src/turf/schema.py
src/turf/schema_util.py
src/turf/testing.py
src/turf.egg-info/PKG-INFO
src/turf.egg-info/SOURCES.txt
src/turf.egg-info/dependency_links.txt
src/turf.egg-info/requires.txt
src/turf.egg-info/top_level.txt