Metadata-Version: 1.0
Name: turf
Version: 1.2.0.post1
Summary: A python configuration library
Home-page: https://github.com/HurricaneLabs/turf
Author: Colton Leekley-Winslow
Author-email: colton@hurricanelabs.com
License: UNKNOWN
Platform: UNKNOWN
